cssbuster.py
setup.py
cssbuster.egg-info/PKG-INFO
cssbuster.egg-info/SOURCES.txt
cssbuster.egg-info/dependency_links.txt
cssbuster.egg-info/entry_points.txt
cssbuster.egg-info/not-zip-safe
cssbuster.egg-info/requires.txt
cssbuster.egg-info/top_level.txt