Metadata-Version: 1.0
Name: cssbuster
Version: 0.1.4
Summary: cssbuster is a simple command line tool to invalidate(when it's necessary) external resources linked to a css file.
Home-page: https://github.com/jorgebastida/cssbuster
Author: Jorge Bastida
Author-email: me@jorgebastida.com
License: BSD
Platform: any
Classifier: Development Status :: 3 - Alpha
Classifier: Environment :: Web Environment
Classifier: Intended Audience :: Developers
Classifier: License :: OSI Approved :: BSD License
Classifier: Operating System :: OS Independent
Classifier: Programming Language :: Python
Classifier: Topic :: Utilities
